pymcws/__init__.py
pymcws/exceptions.py
pymcws/media_server.py
pymcws/model.py
pymcws/server_mixins.py
pymcws/utils.py
pymcws/api/__init__.py
pymcws/api/file.py
pymcws/api/files.py
pymcws/api/library.py
pymcws/api/playback.py
pymcws/api/recipes.py
pymcws-1.1.0.dist-info/LICENSE
pymcws-1.1.0.dist-info/METADATA
pymcws-1.1.0.dist-info/WHEEL
pymcws-1.1.0.dist-info/top_level.txt
pymcws-1.1.0.dist-info/RECORD
