Metadata-Version: 2.1
Name: pymcws
Version: 1.1.0
Summary: Python API for the MCWS interface of JRiver Media Center
Home-page: https://github.com/kenomaerz/pymcws
Author: Keno März
Author-email: keno.maerz@gmail.com
License: MIT
Download-URL: https://pypi.org/project/pymcws/
Keywords: JRiver,MCWS
Platform: UNKNOWN
License-File: LICENSE
Requires-Dist: requests
Requires-Dist: pillow
